<?xml version="1.0" encoding="UTF-8" standalone="yes"?>
<AssignMessage async="false" continueOnError="false" enabled="true" name="AM-set-target-url-place-order">
    <DisplayName>AM-set-target-url-place-order</DisplayName>
    <AssignVariable>
        <Name>target.copy.pathsuffix</Name>
        <Value>false</Value>
    </AssignVariable>
    <AssignVariable>
        <Name>pathSuffix</Name>
        <Value>power/place-order</Value>
    </AssignVariable>
    <IgnoreUnresolvedVariables>true</IgnoreUnresolvedVariables>
    <AssignTo createNew="false" transport="http" type="request"/>
</AssignMessage>